optiq/__init__.py
optiq/callbacks.py
optiq/capture.py
optiq/cli.py
optiq/lightning_modules.py
optiq/torchgeo.py
optiq/api/__init__.py
optiq/api/clients.py
optiq/api/schemas.py
optiq/data/__init__.py
optiq/data/cli.py
optiq/data/datasets.py
optiq/data/frame_sequence.py
optiq/infra/__init__.py
optiq/infra/metrics.py
optiq/io/conditional_motion.py
optiq/io/fbx_continuous_dataset.py
optiq/io/fbx_loader.py
optiq/io/sphere_data.py
optiq/models/__init__.py
optiq/models/conditional_autoreg.py
optiq/models/mlp.py
optiq/models/registry.py
optiq/models/sphere_cnn.py
optiq/models/transformer.py
optiq/models/unet1d.py
optiq/models/unet_autoreg.py
optiq/physics/__init__.py
optiq/physics/config.py
optiq/physics/engine.py
optiq/physics/objects.py
optiq/physics/pybullet_adapter.py
optiq/rl/__init__.py
optiq/rl/adapter.py
optiq/rl/bootstrap.py
optiq/rl/fbx_dataset.py
optiq/rl/humanoid_mapping.py
optiq/robotics/__init__.py
optiq/robotics/robot.py
optiq/robotics/visual_servo.py
optiq/training/conditional_autoreg_runner.py
optiq/training/pipeline.py
optiq/training/sphere_cnn_runner.py
optiq/utils/class_loader.py
optiq/utils/env_loader.py
optiq/vis/__init__.py
optiq/vis/plotly_anim_runner.py
optiq/vis/video.py
optiq-0.1.0.dist-info/licenses/LICENSE
optiq-0.1.0.dist-info/METADATA
optiq-0.1.0.dist-info/WHEEL
optiq-0.1.0.dist-info/entry_points.txt
optiq-0.1.0.dist-info/top_level.txt
optiq-0.1.0.dist-info/RECORD
