Metadata-Version: 2.4
Name: optiq
Version: 0.1.0
Summary: Imitation-first motion learning framework
Author-email: "Ted T." <theador.t@gmail.com>
Maintainer-email: "Ted T." <theador.t@gmail.com>
License: GPL-3.0-or-later
Project-URL: Homepage, https://github.com/tedtroxell/optiq
Project-URL: Repository, https://github.com/tedtroxell/optiq
Project-URL: Documentation, https://optiq.readthedocs.io/
Project-URL: Bug Reports, https://github.com/tedtroxell/optiq/issues
Project-URL: Source, https://github.com/tedtroxell/optiq
Keywords: machine-learning,reinforcement-learning,motion-learning,imitation-learning,robotics,animation,deep-learning,pytorch,computer-vision,simulation
Classifier: Development Status :: 3 - Alpha
Classifier: Intended Audience :: Developers
Classifier: Intended Audience :: Science/Research
Classifier: License :: OSI Approved :: GNU General Public License v3 or later (GPLv3+)
Classifier: Operating System :: OS Independent
Classifier: Programming Language :: Python :: 3
Classifier: Programming Language :: Python :: 3.9
Classifier: Programming Language :: Python :: 3.10
Classifier: Programming Language :: Python :: 3.11
Classifier: Programming Language :: Python :: 3.12
Classifier: Topic :: Scientific/Engineering :: Artificial Intelligence
Classifier: Topic :: Scientific/Engineering :: Image Processing
Classifier: Topic :: Software Development :: Libraries :: Python Modules
Classifier: Framework :: Pytest
Classifier: Framework :: Jupyter
Requires-Python: >=3.9
License-File: LICENSE
Requires-Dist: pydantic
Requires-Dist: httpx>=0.24.0
Requires-Dist: numpy
Requires-Dist: scipy
Requires-Dist: trimesh>=4.10.0
Requires-Dist: pyyaml
Requires-Dist: click
Requires-Dist: torch>=2.8.0
Requires-Dist: mesh-to-sdf>=0.0.15
Requires-Dist: pybullet>=3.2.7
Requires-Dist: torchvista>=0.2.6
Provides-Extra: ml
Requires-Dist: pytorch-lightning==2.4.0; extra == "ml"
Requires-Dist: torchmetrics>=1.8.2; extra == "ml"
Requires-Dist: mlflow<3.0.0,>=2.10.0; extra == "ml"
Requires-Dist: h5py; extra == "ml"
Requires-Dist: pyarrow; extra == "ml"
Requires-Dist: scikit-image>=0.22.0; extra == "ml"
Provides-Extra: rl
Requires-Dist: mujoco; extra == "rl"
Requires-Dist: stable-baselines3>=2.7.0; extra == "rl"
Requires-Dist: gymnasium[mujoco]; extra == "rl"
Provides-Extra: viz
Requires-Dist: plotly>=6.5.0; extra == "viz"
Requires-Dist: moviepy>=2.2.1; extra == "viz"
Requires-Dist: matplotlib; extra == "viz"
Requires-Dist: opencv-python-headless; extra == "viz"
Provides-Extra: web
Requires-Dist: django; extra == "web"
Requires-Dist: channels; extra == "web"
Requires-Dist: daphne; extra == "web"
Requires-Dist: django-crispy-forms; extra == "web"
Requires-Dist: crispy-bootstrap5; extra == "web"
Requires-Dist: sqlmodel>=0.0.27; extra == "web"
Requires-Dist: fastapi>=0.124.0; extra == "web"
Requires-Dist: uvicorn>=0.38.0; extra == "web"
Requires-Dist: jinja2>=3.1.6; extra == "web"
Requires-Dist: python-multipart>=0.0.20; extra == "web"
Requires-Dist: aiofiles>=25.1.0; extra == "web"
Provides-Extra: infra
Requires-Dist: kombu>=5.6.1; extra == "infra"
Requires-Dist: redis>=7.0.1; extra == "infra"
Requires-Dist: prometheus-client>=0.23.1; extra == "infra"
Requires-Dist: psycopg2-binary>=2.9.11; extra == "infra"
Provides-Extra: all
Requires-Dist: optiq[ml]; extra == "all"
Requires-Dist: optiq[rl]; extra == "all"
Requires-Dist: optiq[viz]; extra == "all"
Requires-Dist: optiq[web]; extra == "all"
Requires-Dist: optiq[infra]; extra == "all"
Provides-Extra: dev
Requires-Dist: optiq[all]; extra == "dev"
Requires-Dist: pytest>=8.4.2; extra == "dev"
Requires-Dist: pytest-cov>=4.0.0; extra == "dev"
Requires-Dist: black>=23.0.0; extra == "dev"
Requires-Dist: flake8>=6.0.0; extra == "dev"
Requires-Dist: mypy>=1.0.0; extra == "dev"
Requires-Dist: twine>=4.0.0; extra == "dev"
Requires-Dist: tomli>=1.2.0; python_version < "3.11" and extra == "dev"
Dynamic: license-file
